README.txt
setup.py
taskpromises/__init__.py
taskpromises/promises.py
taskpromises.egg-info/PKG-INFO
taskpromises.egg-info/SOURCES.txt
taskpromises.egg-info/dependency_links.txt
taskpromises.egg-info/top_level.txt