Metadata-Version: 1.1
Name: taskpromises
Version: 0.1.0a1
Summary: An distributed implementation of Promises for Google Appengine Tasks
Home-page: ...
Author: Emlyn O'Regan / Training Evidence Systems Pty Ltd
Author-email: emlyn@tesapp.com
License: Apache License 2.0
Keywords: promises tasks appengine gae
Platform: UNKNOWN
Classifier: Development Status :: 3 - Alpha
Classifier: License :: OSI Approved :: Apache Software License
Classifier: Programming Language :: Python
